quid/__init__.py
quid/cli/QuidCLI.py
quid/cli/__init__.py
quid/core/BestMatch.py
quid/core/InternalMatch.py
quid/core/InternalMatchSpan.py
quid/core/Quid.py
quid/core/QuidMatcher.py
quid/core/QuidMerger.py
quid/core/Text.py
quid/core/Token.py
quid/core/__init__.py
quid/helper/Decoder.py
quid/helper/Loader.py
quid/helper/__init__.py
quid/match/Match.py
quid/match/MatchSpan.py
quid/match/__init__.py
quid/passager/AnalyzedWork.py
quid/passager/CitationSource.py
quid/passager/CitationSourceLink.py
quid/passager/Location.py
quid/passager/Passager.py
quid/passager/SourceSegment.py
quid/passager/TargetLocation.py
quid/passager/TargetLocationSelection.py
quid/passager/TargetMatch.py
quid/passager/TargetText.py
quid/passager/TargetTextLocationLink.py
quid/passager/TextWithMatches.py
quid/passager/__init__.py
quid/visualization/Info.py
quid/visualization/Markup.py
quid/visualization/MarkupSpan.py
quid/visualization/TargetHtml.py
quid/visualization/TargetTextWithContent.py
quid/visualization/Visualization.py
quid/visualization/Visualizer.py
quid/visualization/__init__.py
Quid-2.6.7.dist-info/LICENSE
Quid-2.6.7.dist-info/METADATA
Quid-2.6.7.dist-info/WHEEL
Quid-2.6.7.dist-info/entry_points.txt
Quid-2.6.7.dist-info/top_level.txt
Quid-2.6.7.dist-info/RECORD
