Metadata-Version: 2.1
Name: Quid
Version: 2.6.7
Summary: Quid is a tool for quotation detection in texts and can deal with common properties of quotations, for example, ellipses or inaccurate quotations.
Home-page: https://hu.berlin/quid
Author: Frederik Arnold
Author-email: frederik.arnold@hu-berlin.de
Project-URL: Source, https://hu.berlin/quid
Keywords: quotation detection,quotation identification,literal citation extraction,key passages,natural language processing,nlp,text reuse
Classifier: Programming Language :: Python :: 3
Classifier: License :: OSI Approved :: Apache Software License
Classifier: Operating System :: OS Independent
Requires-Python: >=3.9
License-File: LICENSE
Requires-Dist: yattag>=1.15.2
Requires-Dist: rapidfuzz>=3.6.1
Requires-Dist: datasketch>=1.6.4
Requires-Dist: tqdm>=4.66.3
